pygame_emojis/__init__.py
pygame_emojis/from_fonts.py
pygame_emojis/emojis_data/__init__.py
pygame_emojis/emojis_data/download.py
pygame_emojis/emojis_data/svg.py
pygame_emojis-0.2.0.dist-info/METADATA
pygame_emojis-0.2.0.dist-info/WHEEL
pygame_emojis-0.2.0.dist-info/licenses/LICENSE
pygame_emojis-0.2.0.dist-info/RECORD
