Metadata-Version: 2.4
Name: pygame_emojis
Version: 0.2.0
Summary: API for using emojis in pygame.
Project-URL: Homepage, https://github.com/ScienceGamez/pygame_emojis
Project-URL: Bug Tracker, https://github.com/ScienceGamez/pygame_emojis/issues
Author-email: Lionel42 <lionel@sciencegames.ch>, Bora <boraofficial@duck.com>
License: MIT License
License-File: LICENSE
Classifier: License :: OSI Approved :: MIT License
Classifier: Operating System :: OS Independent
Classifier: Programming Language :: Python :: 3
Requires-Python: >=3.10
Requires-Dist: cairosvg
Requires-Dist: emoji
Requires-Dist: pygame
